celib/celist.py
celib/common.py
celib-0.0.10.dist-info/METADATA
celib-0.0.10.dist-info/WHEEL
celib-0.0.10.dist-info/top_level.txt
celib-0.0.10.dist-info/RECORD
