Metadata-Version: 2.1
Name: celib
Version: 0.0.10
Summary: celib
Home-page: https://github.com/saranae00/celib
Author: cekwak
Author-email: saranae00@gmail.com
License: UNKNOWN
Download-URL: https://github.com/saranae00/celib/archive/refs/tags/0.0.10.tar.gz
Keywords: celib
Platform: UNKNOWN
Classifier: Programming Language :: Python :: 3.6
Classifier: Programming Language :: Python :: 3.7
Classifier: Programming Language :: Python :: 3.8
Classifier: Programming Language :: Python :: 3.9
Requires-Python: >=3.6
Requires-Dist: pandas
Requires-Dist: numpy
Requires-Dist: pathos
